{
    "deal": {
        "features": "- Gets about a phone’s worth of charge in 4-6 hours of sunlight\r\n- Fully charges in sunlight (13 hours) or via USB (4-6 hours)\r\n- 2.1 amp output will charge any smartphone or tablet\r\n- Shave a tiny sliver off your carbon footprint\r\n- Model: CH-SOLRESTOREXL-WHT",
        "id": "a6ki0000000TOj4AAG",
        "items": [
            {
                "attributes": [],
                "condition": "New",
                "id": "102444",
                "price": 14,
                "photo": "https://res.cloudinary.com/mediocre/image/upload/v1429753780/ublulmxubdrr5fyzrtx0.png"
            }
        ],
        "photos": [
            "https://res.cloudinary.com/mediocre/image/upload/v1429842212/lsufnppjsiexbe0c9vfd.png",
            "https://res.cloudinary.com/mediocre/image/upload/v1429818401/sy4n9d9br4oztj5y9lnz.png",
            "https://res.cloudinary.com/mediocre/image/upload/v1429815209/peaiuandajj8mau5plb8.png",
            "https://res.cloudinary.com/mediocre/image/upload/v1429758608/wvq0st9dhselryluol2h.png",
            "https://res.cloudinary.com/mediocre/image/upload/v1429816227/o6ld0a6ov6dodvlnndu1.png",
            "https://res.cloudinary.com/mediocre/image/upload/v1429753780/ublulmxubdrr5fyzrtx0.png",
            "https://res.cloudinary.com/mediocre/image/upload/v1429841931/ma75qgnzqv4s3br4aqyr.png"
        ],
        "title": "ReVIVE 4000mAh Solar Panel Power Bank",
        "specifications": "Specs \r\n====\r\n- Model: CH-SOLRESTOREXL-WHT\r\n- 4,000mAh Li-Po battery\r\n- Output: 2.1A USB\r\n- Fully charge by direct sunlight in 13 hours (280mA)\r\n- Fully charge by USB in 4-6 hours\r\n- Capacity indicator and LED flashlight\r\n- Dimensions: 6.7 x 3.6 x .8 in\r\n- Weight: 8 oz\r\n\r\n**Condition:** New\r\n**Warranty:** [3 Year Accessory Power](http://www.accessorypower.com/warranty)\r\n**Estimated Delivery:** 5/6 - 5/8\r\n**Shipping:** $5 or free with **[VMP](https://mediocre.com/vmp)** \r\n\r\nWhat's in the Box?\r\n====\r\n1x Solar powered power bank\r\n2x Window suction cups\r\n1x Carabiner\r\n1x Solar panel extender [for additional panels](http://www.amazon.com/dp/B00FH5SX3E/&tag=meh0ec-20)\r\n1x USB charging cable\r\n\r\nPictures \r\n====\r\n[Retail box](https://res.cloudinary.com/mediocre/image/upload/v1429753780/ublulmxubdrr5fyzrtx0.png)\r\n[Everything included](https://res.cloudinary.com/mediocre/image/upload/v1429818401/sy4n9d9br4oztj5y9lnz.png)\r\n[Carabiner and top view](https://res.cloudinary.com/mediocre/image/upload/v1429815209/peaiuandajj8mau5plb8.png)\r\n[Outlets](https://res.cloudinary.com/mediocre/image/upload/v1429758608/wvq0st9dhselryluol2h.png)\r\n[Back view](https://res.cloudinary.com/mediocre/image/upload/v1429816227/o6ld0a6ov6dodvlnndu1.png)\r\n\r\nPrice Check\r\n====\r\n[109.99 List, $29.99 at Amazon (sold third party)](http://www.amazon.com/ReVIVE-Series-ReStore-Portable-Charger/dp/B00FH5SX3E/ref=lh_ni_t?ie=UTF8&psc=1&smid=A2ZMWBP05360R6&tag=meh0ec-20)\r\n\r\n*Find a relevant price comparison? Please share it in a reply to this comment :)*",
        "story": {
            "title": "Clean energy done dirt cheap.",
            "body": "2015 will be the year you take the first step toward energy independence. (Or second step, if you already have a solar calculator.) \"Right now I'm running on a mixture of grid electricity and solar,\" you can legitimately say, with a mixture of scorn and pity for your less progressive friends. \r\n\r\n\"But hey, that's just me,\" you continue, the very image of a serene, saintly citizen of Spaceship Earth. \"*I* would prefer *not* to annihilate all life on the planet to provide myself with a few moments of artificial comfort. But I don't expect everyone to have already attained this level of enlightenment.\"\r\n\r\nNo doubt this kind of shaming will inspire your audience into action, to immediately find ways to emulate your example. At least, you assume that's why they're all running off. But who needs them anyway? You've got everything you need: Father Sun, Mother Earth, and your ReVIVE Solar Panel Power Bank.\r\n\r\nNo, not a solar array on your roof. That shit's expensive. Just one of these little solar-powered phone chargers. Leave it in sunshine for a mere 4-6 hours and it'll soak up enough of Sol's terrible fury to... uh, charge your phone, maybe even your tablet. \r\n\r\nOK, so it's not exactly cold fusion. It'd probably be easier to just charge the power bank via USB and use it like a regular non-solar backup battery. But really, that's how energy use changes: bit by bit, one calculator or lightbulb or phone charger at a time. And hey, if you charge it through USB most of the time, well, your friends don't need to know that. It's still more solar than *their* phone chargers."
        },
        "theme": {
            "accentColor": "#007592",
            "backgroundColor": "#c3d7bb",
            "backgroundImage": "https://res.cloudinary.com/mediocre/image/upload/v1429813844/mhanbpa0eywybf9tjha2.jpg",
            "foreground": "dark"
        },
        "url": "https://meh.com/deals/revive-4000mah-solar-panel-power-bank",
        "soldOutAt": "2015-04-24T04:57:10.076Z",
        "topic": {
            "commentCount": 31,
            "createdAt": "2015-04-24T04:00:01.018Z",
            "id": "5539bfc118d9299c0aee1406",
            "replyCount": 15,
            "url": "https://meh.com/forum/topics/revive-4000mah-solar-panel-power-bank",
            "voteCount": 1
        }
    },
    "poll": {
        "answers": [
            {
                "id": "a6li0000000PCh9AAG-1",
                "text": "Solar",
                "voteCount": 90
            },
            {
                "id": "a6li0000000PCh9AAG-2",
                "text": "Wind",
                "voteCount": 35
            },
            {
                "id": "a6li0000000PCh9AAG-3",
                "text": "Hydro",
                "voteCount": 10
            },
            {
                "id": "a6li0000000PCh9AAG-4",
                "text": "Nuclear",
                "voteCount": 92
            },
            {
                "id": "a6li0000000PCh9AAG-5",
                "text": "Biofuels",
                "voteCount": 11
            },
            {
                "id": "a6li0000000PCh9AAG-6",
                "text": "A judicious balance of sources is the best defense against future economic and environmental turmoil",
                "voteCount": 135
            },
            {
                "id": "a6li0000000PCh9AAG-7",
                "text": "WE'RE DOOMED WE'RE ALL DOOMED",
                "voteCount": 110
            },
            {
                "id": "a6li0000000PCh9AAG-8",
                "text": "Some other answer you'll burn in the forum",
                "voteCount": 4
            }
        ],
        "id": "a6li0000000PCh9AAG",
        "startDate": "2015-04-24T04:00:00.000Z",
        "title": "What form of alternative energy do you think will take the lead in solving our climate and consumption problems?",
        "topic": {
            "commentCount": 6,
            "createdAt": "2015-04-24T04:00:10.486Z",
            "id": "5539bfca18d9299c0aee140a",
            "replyCount": 2,
            "url": "https://meh.com/forum/topics/what-form-of-alternative-energy-do-you-think-will-take-the-lead-in-solving-our-climate-and-consumption-problems",
            "voteCount": 1
        }
    },
    "video": {
        "id": "a6li0000000PCh9AAG",
        "startDate": "2015-04-24T04:00:00.000Z",
        "title": "Komedy Kornhole Open Mic Friday",
        "url": "https://www.youtube.com/watch?v=psmuDFMZULM",
        "topic": {
            "commentCount": 1,
            "createdAt": "2015-04-24T04:00:09.469Z",
            "id": "5539bfc93f4c14b80a622c55",
            "replyCount": 0,
            "url": "https://meh.com/forum/topics/komedy-kornhole-open-mic-friday-15",
            "voteCount": 1
        }
    }
}